{"coord": {"lon": 139.6917, "lat": 35.6895}, "weather": [{"id": 501, "main": "Rain", "description": "moderate rain", "icon": "10d"}], "base": "stations", "main": {"temp": 287.04, "feels_like": 286.34, "temp_min": 285.14, "temp_max": 288.5, "pressure": 1018, "humidity": 71}, "visibility": 10000, "wind": {"speed": 2.57, "deg": 190}, "rain": {"1h": 2.05}, "clouds": {"all": 75}, "dt": 1711266002, "sys": {"type": 2, "id": 2001249, "country": "JP", "sunrise": 1711226354, "sunset": 1711270541}, "timezone": 32400, "id": 1850147, "name": "Tokyo", "cod": 200}